{
  "invoices": [
    {
      "senderName": "Fabulous Enterprise",
      "senderPhone": "+3869892713115",
      "senderAddress": "1331 Hart Ridge Road 48436 Gaines, MI",
      "senderEmail": "info@fabulousenterprise.co",
      "customerName": "abduljelel ahmed",
      "customerPhone": "Rose",
      "customerAddress": "Frank Ocean",
      "customerEmail": "abduljelelahmed@gmail.com",
      "issueDate": "2025-09-27",
      "dueDate": "2025-09-28",
      "billingCurrency": "USD",
      "items": [
        {
          "name": "Item",
          "quantity": 344,
          "price": 2882,
          "total": 991408,
          "id": "it_sfh9wjr7"
        }
      ],
      "subtotal": 991408,
      "discount": 17,
      "totalDue": 991391,
      "status": "PAID",
      "paymentInfo": {
        "accountName": "Jures",
        "accountNumber": "09988833",
        "achRoutingNo": "23938333",
        "bankName": "Banking",
        "bankAddress": "10 Mountain Road"
      },
      "reminders": {
        "14days": false,
        "7days": false,
        "3days": false,
        "24hrs": true,
        "dueDate": true
      },
      "activities": [
        {
          "id": "act_ghx9hdfa",
          "type": "CREATED",
          "user": "System",
          "timestamp": "2025-09-25T14:40:08.355Z",
          "description": "Created invoice INV 6526104-6136 / abduljelel ahmed"
        }
      ],
      "notes": "",
      "id": "inv_47azs5lo",
      "invoiceNumber": "INV 6526104-6136"
    },
    {
      "senderName": "Fabulous Enterprise",
      "senderPhone": "+3869892713115",
      "senderAddress": "1331 Hart Ridge Road 48436 Gaines, MI",
      "senderEmail": "info@fabulousenterprise.co",
      "customerName": "abduljelel ahmed",
      "customerPhone": "08154085965",
      "customerAddress": "10, Rufa Isiri Street, Aviele, Edo State",
      "customerEmail": "abduljelelahmed@gmail.com",
      "issueDate": "2025-09-25",
      "dueDate": "2025-09-26",
      "billingCurrency": "EUR",
      "items": [
        {
          "name": "Itemizes",
          "quantity": 132,
          "price": 9393,
          "total": 1239876,
          "id": "it_x2srg9ff"
        }
      ],
      "subtotal": 1239876,
      "discount": 23,
      "totalDue": 1239853,
      "status": "PARTIAL",
      "paymentInfo": {
        "accountName": "Bank",
        "accountNumber": "2238383",
        "achRoutingNo": "3837373",
        "bankName": "Jili",
        "bankAddress": "10, Rufa Isiri Street, Aviele, Edo State"
      },
      "reminders": {
        "14days": true,
        "7days": false,
        "3days": false,
        "24hrs": true,
        "dueDate": false
      },
      "activities": [
        {
          "id": "act_owyag206",
          "type": "CREATED",
          "user": "System",
          "timestamp": "2025-09-25T14:38:22.181Z",
          "description": "Created invoice INV 8171159-2480 / abduljelel ahmed"
        }
      ],
      "notes": "Note",
      "id": "inv_w0xvoshj",
      "invoiceNumber": "INV 8171159-2480"
    },
    {
      "senderName": "Fabulous Enterprise",
      "senderPhone": "+3869892713115",
      "senderAddress": "1331 Hart Ridge Road 48436 Gaines, MI",
      "senderEmail": "info@fabulousenterprise.co",
      "customerName": "abduljelel ahmed",
      "customerPhone": "08154085965",
      "customerAddress": "10, Rufa Isiri Street, Aviele, Edo State",
      "customerEmail": "abduljelelahmed@gmail.com",
      "issueDate": "2025-09-25",
      "dueDate": "2025-09-26",
      "billingCurrency": "EUR",
      "items": [
        {
          "name": "Itemizes",
          "quantity": 132,
          "price": 9393,
          "total": 1239876,
          "id": "it_5yexnhqs"
        }
      ],
      "subtotal": 1239876,
      "discount": 23,
      "totalDue": 1239853,
      "status": "PARTIAL",
      "paymentInfo": {
        "accountName": "Bank",
        "accountNumber": "2238383",
        "achRoutingNo": "3837373",
        "bankName": "Jili",
        "bankAddress": "10, Rufa Isiri Street, Aviele, Edo State"
      },
      "reminders": {
        "14days": true,
        "7days": false,
        "3days": false,
        "24hrs": true,
        "dueDate": false
      },
      "activities": [
        {
          "id": "act_ng84gmpi",
          "type": "CREATED",
          "user": "System",
          "timestamp": "2025-09-25T14:37:17.600Z",
          "description": "Created invoice INV 3119030-6698 / abduljelel ahmed"
        }
      ],
      "notes": "Note",
      "id": "inv_ndezkdtk",
      "invoiceNumber": "INV 3119030-6698"
    },
    {
      "senderName": "Fabulous Enterprise",
      "senderPhone": "+3869892713115",
      "senderAddress": "1331 Hart Ridge Road 48436 Gaines, MI",
      "senderEmail": "info@fabulousenterprise.co",
      "customerName": "abduljelel ahmed",
      "customerPhone": "08154085965",
      "customerAddress": "10, Rufa Isiri Street, Aviele, Edo State",
      "customerEmail": "abduljelelahmed@gmail.com",
      "issueDate": "2025-09-25",
      "dueDate": "2025-09-16",
      "billingCurrency": "USD",
      "items": [
        {
          "name": "Tile",
          "quantity": 2,
          "price": 3442,
          "total": 6884,
          "id": "it_jumwl9io"
        }
      ],
      "subtotal": 6884,
      "discount": 3,
      "totalDue": 6881,
      "status": "PARTIAL",
      "paymentInfo": {
        "accountName": "BAnk",
        "accountNumber": "Accounts",
        "achRoutingNo": "888333",
        "bankName": "Savings",
        "bankAddress": "10 Mountain Road"
      },
      "reminders": {
        "14days": false,
        "7days": true,
        "3days": true,
        "24hrs": false,
        "dueDate": true
      },
      "activities": [
        {
          "id": "act_7tv57gn8",
          "type": "CREATED",
          "user": "System",
          "timestamp": "2025-09-25T14:35:24.487Z",
          "description": "Created invoice INV 5694245-2312 / abduljelel ahmed"
        }
      ],
      "notes": "Notes",
      "id": "inv_9xyufjp8",
      "invoiceNumber": "INV 5694245-2312"
    },
    {
      "senderName": "Fabulous Enterprise",
      "senderPhone": "+3869892713115",
      "senderAddress": "1331 Hart Ridge Road 48436 Gaines, MI",
      "senderEmail": "info@fabulousenterprise.co",
      "customerName": "abduljelel ahmed",
      "customerPhone": "08154085965",
      "customerAddress": "10, Rufa Isiri Street, Aviele, Edo State",
      "customerEmail": "abduljelelahmed@gmail.com",
      "issueDate": "2025-09-25",
      "dueDate": "2025-09-03",
      "billingCurrency": "EUR",
      "items": [
        {
          "name": "mm",
          "quantity": 1,
          "price": -1,
          "total": -1,
          "id": "it_nn5h62rj"
        },
        {
          "name": "",
          "quantity": 1,
          "price": 0,
          "total": 0,
          "id": "it_b64ggw8a"
        }
      ],
      "subtotal": -1,
      "discount": 0,
      "totalDue": -1,
      "status": "DRAFT",
      "paymentInfo": {
        "accountName": "o",
        "accountNumber": "",
        "achRoutingNo": "",
        "bankName": "",
        "bankAddress": ""
      },
      "reminders": {
        "14days": false,
        "7days": true,
        "3days": true,
        "24hrs": false,
        "dueDate": false
      },
      "activities": [
        {
          "id": "act_4dykw0vy",
          "type": "CREATED",
          "user": "System",
          "timestamp": "2025-09-25T14:33:21.455Z",
          "description": "Created invoice INV 7478356-1090 / abduljelel ahmed"
        }
      ],
      "notes": "",
      "id": "inv_q2blz45w",
      "invoiceNumber": "INV 7478356-1090"
    },
    {
      "senderName": "Fabulous Enterprise",
      "senderPhone": "+3869892713115",
      "senderAddress": "1331 Hart Ridge Road 48436 Gaines, MI",
      "senderEmail": "info@fabulousenterprise.co",
      "customerName": "Destiny Edeki",
      "customerPhone": "099300",
      "customerAddress": "10 Mountain Road",
      "customerEmail": "abduljelelahmed@gmail.com",
      "issueDate": "2025-09-27",
      "dueDate": "2025-09-30",
      "billingCurrency": "EUR",
      "items": [
        {
          "name": "Caricature",
          "quantity": 221,
          "price": 99,
          "total": 21879,
          "id": "it_z49hyuq5"
        }
      ],
      "subtotal": 21879,
      "discount": 3,
      "totalDue": 21876,
      "status": "DRAFT",
      "paymentInfo": {
        "accountName": "12838483",
        "accountNumber": "23993832",
        "achRoutingNo": "393933",
        "bankName": "Serendipity",
        "bankAddress": "10 Mountain Road"
      },
      "reminders": {
        "14days": true,
        "7days": false,
        "3days": false,
        "24hrs": false,
        "dueDate": true
      },
      "activities": [
        {
          "id": "act_c9wzj0no",
          "type": "CREATED",
          "user": "System",
          "timestamp": "2025-09-25T13:02:36.726Z",
          "description": "Created invoice INV 3872662-3667 / Destiny Edeki"
        }
      ],
      "notes": "Notes",
      "id": "inv_he1edig6",
      "invoiceNumber": "INV 3872662-3667"
    },
    {
      "senderName": "Fabulous Enterprise",
      "senderPhone": "+3869892713115",
      "senderAddress": "1331 Hart Ridge Road 48436 Gaines, MI",
      "senderEmail": "info@fabulousenterprise.co",
      "customerName": "Destiny Edeki",
      "customerPhone": "099300",
      "customerAddress": "10 Mountain Road",
      "customerEmail": "abduljelelahmed@gmail.com",
      "issueDate": "2025-09-27",
      "dueDate": "2025-09-30",
      "billingCurrency": "EUR",
      "items": [
        {
          "name": "Caricature",
          "quantity": 2,
          "price": 99,
          "total": 198,
          "id": "it_umvqrkff"
        }
      ],
      "subtotal": 198,
      "discount": 3,
      "totalDue": 195,
      "status": "OVERDUE",
      "paymentInfo": {
        "accountName": "12838483",
        "accountNumber": "23993832",
        "achRoutingNo": "393933",
        "bankName": "Serendipity",
        "bankAddress": "10 Mountain Road"
      },
      "reminders": {
        "14days": true,
        "7days": false,
        "3days": false,
        "24hrs": false,
        "dueDate": true
      },
      "activities": [
        {
          "id": "act_frrgz4fi",
          "type": "CREATED",
          "user": "System",
          "timestamp": "2025-09-25T13:02:22.807Z",
          "description": "Created invoice INV 4121909-5497 / Destiny Edeki"
        }
      ],
      "notes": "Notes",
      "id": "inv_w70qxctm",
      "invoiceNumber": "INV 4121909-5497"
    },
    {
      "senderName": "Fabulous Enterprise",
      "senderPhone": "+3869892713115",
      "senderAddress": "1331 Hart Ridge Road 48436 Gaines, MI",
      "senderEmail": "info@fabulousenterprise.co",
      "customerName": "Destiny Edeki",
      "customerPhone": "099300",
      "customerAddress": "10 Mountain Road",
      "customerEmail": "abduljelelahmed@gmail.com",
      "issueDate": "2025-09-27",
      "dueDate": "2025-09-30",
      "billingCurrency": "EUR",
      "items": [
        {
          "name": "Caricature",
          "quantity": 2,
          "price": 190,
          "total": 380,
          "id": "it_q82zeprg"
        }
      ],
      "subtotal": 380,
      "discount": 3,
      "totalDue": 377,
      "status": "OVERDUE",
      "paymentInfo": {
        "accountName": "12838483",
        "accountNumber": "23993832",
        "achRoutingNo": "393933",
        "bankName": "Serendipity",
        "bankAddress": "10 Mountain Road"
      },
      "reminders": {
        "14days": true,
        "7days": false,
        "3days": false,
        "24hrs": false,
        "dueDate": true
      },
      "activities": [
        {
          "id": "act_plffn0yf",
          "type": "CREATED",
          "user": "System",
          "timestamp": "2025-09-25T13:02:08.494Z",
          "description": "Created invoice INV 1395600-4820 / Destiny Edeki"
        }
      ],
      "notes": "Notes",
      "id": "inv_rbqloshq",
      "invoiceNumber": "INV 1395600-4820"
    },
    {
      "senderName": "Fabulous Enterprise",
      "senderPhone": "+3869892713115",
      "senderAddress": "1331 Hart Ridge Road 48436 Gaines, MI",
      "senderEmail": "info@fabulousenterprise.co",
      "customerName": "Destiny Edeki",
      "customerPhone": "099300",
      "customerAddress": "10 Mountain Road",
      "customerEmail": "abduljelelahmed@gmail.com",
      "issueDate": "2025-09-27",
      "dueDate": "2025-09-30",
      "billingCurrency": "EUR",
      "items": [
        {
          "name": "Caricature",
          "quantity": 2,
          "price": 40,
          "total": 80,
          "id": "it_u39h53uo"
        }
      ],
      "subtotal": 80,
      "discount": 3,
      "totalDue": 77,
      "status": "OVERDUE",
      "paymentInfo": {
        "accountName": "12838483",
        "accountNumber": "23993832",
        "achRoutingNo": "393933",
        "bankName": "Serendipity",
        "bankAddress": "10 Mountain Road"
      },
      "reminders": {
        "14days": true,
        "7days": false,
        "3days": false,
        "24hrs": false,
        "dueDate": true
      },
      "activities": [
        {
          "id": "act_3fq9jkp9",
          "type": "CREATED",
          "user": "System",
          "timestamp": "2025-09-25T13:01:43.213Z",
          "description": "Created invoice INV 8701434-9531 / Destiny Edeki"
        }
      ],
      "notes": "Notes",
      "id": "inv_mrj18ghr",
      "invoiceNumber": "INV 8701434-9531"
    },
    {
      "senderName": "Fabulous Enterprise",
      "senderPhone": "+3869892713115",
      "senderAddress": "1331 Hart Ridge Road 48436 Gaines, MI",
      "senderEmail": "info@fabulousenterprise.co",
      "customerName": "Destiny",
      "customerPhone": "099300303",
      "customerAddress": "10 Mountain Road",
      "customerEmail": "abduljelelahmed@gmail.com",
      "issueDate": "2025-09-27",
      "dueDate": "2025-09-30",
      "billingCurrency": "EUR",
      "items": [
        {
          "name": "Caricature",
          "quantity": 2,
          "price": 40,
          "total": 80,
          "id": "it_a9zoy0vl"
        }
      ],
      "subtotal": 80,
      "discount": 3,
      "totalDue": 77,
      "status": "OVERDUE",
      "paymentInfo": {
        "accountName": "12838483",
        "accountNumber": "23993832",
        "achRoutingNo": "393933",
        "bankName": "Serendipity",
        "bankAddress": "10 Mountain Road"
      },
      "reminders": {
        "14days": true,
        "7days": false,
        "3days": false,
        "24hrs": false,
        "dueDate": true
      },
      "activities": [
        {
          "id": "act_vtn0f084",
          "type": "CREATED",
          "user": "System",
          "timestamp": "2025-09-25T13:01:20.131Z",
          "description": "Created invoice INV 2263842-4976 / Destiny"
        }
      ],
      "notes": "Notes",
      "id": "inv_omrxf8zn",
      "invoiceNumber": "INV 2263842-4976"
    },
    {
      "senderName": "Fabulous Enterprise",
      "senderPhone": "+3869892713115",
      "senderAddress": "1331 Hart Ridge Road 48436 Gaines, MI",
      "senderEmail": "info@fabulousenterprise.co",
      "customerName": "Wisefares",
      "customerPhone": "0990222222",
      "customerAddress": "10 Mountain Road",
      "customerEmail": "frantic@ai.com",
      "issueDate": "2025-09-25",
      "dueDate": "2025-09-30",
      "billingCurrency": "EUR",
      "items": [
        {
          "name": "Destiny make vie",
          "quantity": 9,
          "price": 33,
          "total": 297,
          "id": "it_vucepofe"
        },
        {
          "name": "",
          "quantity": 1,
          "price": 0,
          "total": 0,
          "id": "it_gxqenbvy"
        }
      ],
      "subtotal": 297,
      "discount": 3,
      "totalDue": 294,
      "status": "PARTIAL",
      "paymentInfo": {
        "accountName": "Ross",
        "accountNumber": "29938383",
        "achRoutingNo": "238838343",
        "bankName": "29292223",
        "bankAddress": "10, Rufa Isiri Street, Aviele, Edo State"
      },
      "reminders": {
        "14days": true,
        "7days": true,
        "3days": false,
        "24hrs": false,
        "dueDate": false
      },
      "activities": [
        {
          "id": "act_2c593udn",
          "type": "CREATED",
          "user": "System",
          "timestamp": "2025-09-25T11:51:37.790Z",
          "description": "Created invoice INV 2615976-7928 / Wisefares"
        }
      ],
      "notes": "Thanks",
      "id": "inv_ftvm4jl5",
      "invoiceNumber": "INV 2615976-7928"
    },
    {
      "senderName": "Fabulous Enterprise",
      "senderPhone": "+3869892713115",
      "senderAddress": "1331 Hart Ridge Road 48436 Gaines, MI",
      "senderEmail": "info@fabulousenterprise.co",
      "customerName": "Lisa Caplin",
      "customerPhone": "Ritta",
      "customerAddress": "10 Mountain Road, Destina",
      "customerEmail": "lisa@camplain",
      "issueDate": "2025-09-25",
      "dueDate": "2025-09-26",
      "billingCurrency": "USD",
      "items": [
        {
          "name": "Frank Castle",
          "quantity": 8,
          "price": 5,
          "total": 40,
          "id": "it_j3qxao8i"
        },
        {
          "name": "Ship Building",
          "quantity": 4,
          "price": 7499,
          "total": 29996,
          "id": "it_8btn74kl"
        }
      ],
      "subtotal": 30036,
      "discount": 34,
      "totalDue": 30002,
      "status": "PAID",
      "paymentInfo": {
        "accountName": "Rosebank",
        "accountNumber": "099902022",
        "achRoutingNo": "232234",
        "bankName": "Creditor",
        "bankAddress": "10 Mountain Road"
      },
      "reminders": {
        "14days": false,
        "7days": true,
        "3days": false,
        "24hrs": false,
        "dueDate": true
      },
      "activities": [
        {
          "id": "act_8lz6ejew",
          "type": "CREATED",
          "user": "System",
          "timestamp": "2025-09-25T09:43:25.227Z",
          "description": "Created invoice INV 2404346-4993 / Lisa Caplin"
        }
      ],
      "notes": "Frankly Speaking",
      "id": "inv_1t9bntiy",
      "invoiceNumber": "INV 2404346-4993"
    },
    {
      "senderName": "Fabulous Enterprise",
      "senderPhone": "+3869892713115",
      "senderAddress": "1331 Hart Ridge Road 48436 Gaines, MI",
      "senderEmail": "info@fabulousenterprise.co",
      "customerName": "Make Savior",
      "customerPhone": "88729992",
      "customerAddress": "ABJ",
      "customerEmail": "savior@mark.com",
      "issueDate": "2025-09-25",
      "dueDate": "2025-09-29",
      "billingCurrency": "USD",
      "items": [
        {
          "name": "Power Tools",
          "quantity": 13,
          "price": 40,
          "total": 520,
          "id": "it_p0qq2cq2"
        }
      ],
      "subtotal": 520,
      "discount": 2,
      "totalDue": 518,
      "status": "OVERDUE",
      "paymentInfo": {
        "accountName": "Franca",
        "accountNumber": "292383292",
        "achRoutingNo": "3848483",
        "bankName": "Credi Bank",
        "bankAddress": "10 Mountain Road, Nigeria"
      },
      "reminders": {
        "14days": true,
        "7days": true,
        "3days": false,
        "24hrs": false,
        "dueDate": false
      },
      "activities": [
        {
          "id": "act_z1yynhf5",
          "type": "CREATED",
          "user": "System",
          "timestamp": "2025-09-25T09:25:32.117Z",
          "description": "Created invoice INV 7709856-1622 / Make Savior"
        }
      ],
      "notes": "",
      "id": "inv_qzvkmsmh",
      "invoiceNumber": "INV 7709856-1622"
    },
    {
      "senderName": "Fabulous Enterprise",
      "senderPhone": "+3869892713115",
      "senderAddress": "1331 Hart Ridge Road 48436 Gaines, MI",
      "senderEmail": "info@fabulousenterprise.co",
      "customerName": "abduljelel ahmed",
      "customerPhone": "08154085965",
      "customerAddress": "10, Rufa Isiri Street, Aviele, Edo State",
      "customerEmail": "abduljelelahmed@gmail.com",
      "issueDate": "2025-09-25",
      "dueDate": "2025-09-30",
      "billingCurrency": "EUR",
      "items": [
        {
          "name": "House Cleaning",
          "quantity": 1,
          "price": 133,
          "total": 133,
          "id": "it_akvtey54"
        }
      ],
      "subtotal": 133,
      "discount": 2,
      "totalDue": 131,
      "status": "OVERDUE",
      "paymentInfo": {
        "accountName": "RT",
        "accountNumber": "99902922",
        "achRoutingNo": "ITrate",
        "bankName": "33838332",
        "bankAddress": "10, Rufa Isiri Street, Aviele, Edo State"
      },
      "reminders": {
        "14days": false,
        "7days": true,
        "3days": false,
        "24hrs": false,
        "dueDate": false
      },
      "activities": [
        {
          "id": "act_uh2igu8q",
          "type": "CREATED",
          "user": "System",
          "timestamp": "2025-09-25T09:16:34.343Z",
          "description": "Created invoice undefined / abduljelel ahmed"
        }
      ],
      "notes": "Thanks",
      "id": "inv_en4ai9q9",
      "invoiceNumber": "INV 7262165-7049"
    },
    {
      "senderName": "Fabulous Enterprise",
      "senderPhone": "+3869892713115",
      "senderAddress": "1331 Hart Ridge Road 48436 Gaines, MI",
      "senderEmail": "info@fabulousenterprise.co",
      "customerName": "Soe Enterprises",
      "customerPhone": "0992002922",
      "customerAddress": "10 Mountain Road",
      "customerEmail": "abduljelelahmed@gmail.com",
      "issueDate": "2025-09-25",
      "dueDate": "2025-10-15",
      "billingCurrency": "USD",
      "items": [
        {
          "name": "Fryer Locks",
          "quantity": 5,
          "price": 78,
          "total": 390,
          "id": "it_uav6u9kg"
        },
        {
          "name": "Furniture",
          "quantity": 6,
          "price": 6,
          "total": 36,
          "id": "it_bofz8y8l"
        }
      ],
      "subtotal": 426,
      "discount": 30,
      "totalDue": 396,
      "status": "PARTIAL",
      "paymentInfo": {
        "accountName": "Lisboa",
        "accountNumber": "827272722",
        "achRoutingNo": "899393",
        "bankName": "Castle Bank",
        "bankAddress": "10 Mountain Road"
      },
      "reminders": {
        "14days": false,
        "7days": true,
        "3days": false,
        "24hrs": false,
        "dueDate": false
      },
      "activities": [],
      "notes": "Thank You",
      "id": "inv_5ky3jxhl",
      "invoiceNumber": "INV 5437294-8696"
    },
    {
      "senderName": "Fabulous Enterprise",
      "senderPhone": "+3869892713115",
      "senderAddress": "1331 Hart Ridge Road 48436 Gaines, MI",
      "senderEmail": "info@fabulousenterprise.co",
      "customerName": "Messi Lionel",
      "customerPhone": "9077322",
      "customerAddress": "Frank Casle 40",
      "customerEmail": "castle@mssi.com",
      "issueDate": "2025-09-18",
      "dueDate": "2025-09-30",
      "billingCurrency": "USD",
      "items": [
        {
          "name": "Groceries",
          "quantity": 9,
          "price": 399,
          "total": 3591,
          "id": "it_3a0jkp7i"
        },
        {
          "name": "Repairs",
          "quantity": 3,
          "price": 5,
          "total": 15,
          "id": "it_xqdrygda"
        },
        {
          "name": "reminders",
          "quantity": 9,
          "price": 45,
          "total": 405,
          "id": "it_u1mco5t0"
        }
      ],
      "subtotal": 4011,
      "discount": 3,
      "totalDue": 4008,
      "status": "PAID",
      "paymentInfo": {
        "accountName": "Menu Backerc",
        "accountNumber": "0222029922",
        "achRoutingNo": "(009099)",
        "bankName": "F.IT",
        "bankAddress": "10 Mountain Road, Drive"
      },
      "reminders": {
        "14days": true,
        "7days": true,
        "3days": false,
        "24hrs": false,
        "dueDate": false
      },
      "activities": [],
      "notes": "Thank You",
      "id": "inv_1fys4r1r",
      "invoiceNumber": "INV 9849801-7354"
    },
    {
      "senderName": "Fabulous Enterprise",
      "senderPhone": "+3869892713115",
      "senderAddress": "1331 Hart Ridge Road 48436 Gaines, MI",
      "senderEmail": "info@fabulousenterprise.co",
      "customerName": "Messi Lionel",
      "customerPhone": "9077322",
      "customerAddress": "Frank Casle 40",
      "customerEmail": "castle@mssi.com",
      "issueDate": "2025-09-24",
      "dueDate": "2025-09-30",
      "billingCurrency": "USD",
      "items": [
        {
          "name": "Groceries",
          "quantity": 9,
          "price": 399,
          "total": 3591,
          "id": "it_wdj9r0u5"
        },
        {
          "name": "Repairs",
          "quantity": 3,
          "price": 5,
          "total": 15,
          "id": "it_d4thelul"
        },
        {
          "name": "reminders",
          "quantity": 9,
          "price": 45,
          "total": 405,
          "id": "it_jrelbp8b"
        }
      ],
      "subtotal": 4011,
      "discount": 3,
      "totalDue": 4008,
      "status": "PAID",
      "paymentInfo": {
        "accountName": "Menu Backerc",
        "accountNumber": "0222029922",
        "achRoutingNo": "(009099)",
        "bankName": "F.IT",
        "bankAddress": "10 Mountain Road, Drive"
      },
      "reminders": {
        "14days": true,
        "7days": true,
        "3days": false,
        "24hrs": false,
        "dueDate": false
      },
      "activities": [],
      "notes": "Thank You",
      "id": "inv_2xqy91or",
      "invoiceNumber": "INV 3450557-9100"
    },
    {
      "senderName": "Fabulous Enterprise",
      "senderPhone": "+3869892713115",
      "senderAddress": "1331 Hart Ridge Road 48436 Gaines, MI",
      "senderEmail": "info@fabulousenterprise.co",
      "customerName": "Messi Lionel",
      "customerPhone": "9077322",
      "customerAddress": "Frank Casle 40",
      "customerEmail": "castle@mssi.com",
      "issueDate": "2025-09-24",
      "dueDate": "2025-09-30",
      "billingCurrency": "USD",
      "items": [
        {
          "name": "Groceries",
          "quantity": 9,
          "price": 399,
          "total": 3591,
          "id": "it_54benjf9"
        },
        {
          "name": "Repairs",
          "quantity": 3,
          "price": 5,
          "total": 15,
          "id": "it_b9t8fwdg"
        }
      ],
      "subtotal": 3606,
      "discount": 3,
      "totalDue": 3603,
      "status": "PAID",
      "paymentInfo": {
        "accountName": "Menu Backerc",
        "accountNumber": "0222029922",
        "achRoutingNo": "(009099)",
        "bankName": "F.IT",
        "bankAddress": "10 Mountain Road, Drive"
      },
      "reminders": {
        "14days": true,
        "7days": false,
        "3days": false,
        "24hrs": false,
        "dueDate": false
      },
      "activities": [],
      "notes": "Thank You",
      "id": "inv_jiyx2kkf",
      "invoiceNumber": "INV 3112340-2746"
    },
    {
      "senderName": "Fabulous Enterprise",
      "senderPhone": "+3869892713115",
      "senderAddress": "1331 Hart Ridge Road 48436 Gaines, MI",
      "senderEmail": "info@fabulousenterprise.co",
      "customerName": "Messi Lionel",
      "customerPhone": "9077322",
      "customerAddress": "Frank Casle 40",
      "customerEmail": "castle@mssi.com",
      "issueDate": "2025-09-25",
      "dueDate": "2025-09-30",
      "billingCurrency": "USD",
      "items": [
        {
          "name": "Groceries",
          "quantity": 9,
          "price": 399,
          "total": 3591,
          "id": "it_grmc82nf"
        },
        {
          "name": "Repairs",
          "quantity": 3,
          "price": 5,
          "total": 15,
          "id": "it_e2m0ei93"
        }
      ],
      "subtotal": 3606,
      "discount": 3,
      "totalDue": 3603,
      "status": "PAID",
      "paymentInfo": {
        "accountName": "Menu Backerc",
        "accountNumber": "0222029922",
        "achRoutingNo": "(009099)",
        "bankName": "F.IT",
        "bankAddress": "10 Mountain Road, Drive"
      },
      "reminders": {
        "14days": true,
        "7days": false,
        "3days": false,
        "24hrs": false,
        "dueDate": false
      },
      "activities": [],
      "notes": "Thank You",
      "id": "inv_6dclco7c",
      "invoiceNumber": "INV 3323169-3697"
    },
    {
      "senderName": "Fabulous Enterprise",
      "senderPhone": "+3869892713115",
      "senderAddress": "1331 Hart Ridge Road 48436 Gaines, MI",
      "senderEmail": "info@fabulousenterprise.co",
      "customerName": "Messi Lionel",
      "customerPhone": "9077322",
      "customerAddress": "Frank Casle 40",
      "customerEmail": "castle@mssi.com",
      "issueDate": "2025-09-25",
      "dueDate": "2025-09-30",
      "billingCurrency": "USD",
      "items": [
        {
          "name": "Groceries",
          "quantity": 9,
          "price": 399,
          "total": 3591,
          "id": "it_zkyrdhme"
        },
        {
          "name": "Repairs",
          "quantity": 3,
          "price": 5,
          "total": 15,
          "id": "it_c5pgz6i9"
        }
      ],
      "subtotal": 3606,
      "discount": 3,
      "totalDue": 3603,
      "status": "PAID",
      "paymentInfo": {
        "accountName": "Menu Backerc",
        "accountNumber": "0222029922",
        "achRoutingNo": "(009099)",
        "bankName": "F.IT",
        "bankAddress": "10 Mountain Road, Drive"
      },
      "reminders": {
        "14days": true,
        "7days": false,
        "3days": false,
        "24hrs": false,
        "dueDate": false
      },
      "activities": [],
      "notes": "Thank You",
      "id": "inv_zubuq317",
      "invoiceNumber": "INV 3317852-5423"
    },
    {
      "senderName": "Fabulous Enterprise",
      "senderPhone": "+3869892713115",
      "senderAddress": "1331 Hart Ridge Road 48436 Gaines, MI",
      "senderEmail": "info@fabulousenterprise.co",
      "customerName": "Fran Castle",
      "customerPhone": "590558644",
      "customerAddress": "Ross Aveneu",
      "customerEmail": "abduljelel@gmail.com",
      "issueDate": "2025-09-25",
      "dueDate": "2025-09-29",
      "billingCurrency": "USD",
      "items": [
        {
          "name": "Generator",
          "quantity": 32,
          "price": 5,
          "total": 160,
          "id": "it_jyi1jx7n"
        },
        {
          "name": "Legal Fees",
          "quantity": 6,
          "price": 522,
          "total": 3132,
          "id": "it_vqo33uij"
        }
      ],
      "subtotal": 3292,
      "discount": 30,
      "totalDue": 3262,
      "status": "PARTIAL",
      "paymentInfo": {
        "accountName": "Manager",
        "accountNumber": "0938373892",
        "achRoutingNo": "09899",
        "bankName": "F.I.T",
        "bankAddress": "10 Mountain Road"
      },
      "reminders": {
        "14days": true,
        "7days": true,
        "3days": false,
        "24hrs": false,
        "dueDate": true
      },
      "activities": [],
      "notes": "Note",
      "id": "inv_172wfmlg",
      "invoiceNumber": "INV 7289-3275"
    },
    {
      "senderName": "Fabulous Enterprise",
      "senderPhone": "+3869892713115",
      "senderAddress": "1331 Hart Ridge Road 48436 Gaines, MI",
      "senderEmail": "info@fabulousenterprise.co",
      "customerName": "abduljelel ahmed",
      "customerPhone": "08154085965",
      "customerAddress": "10, Rufa Isiri Street, Aviele, Edo State",
      "customerEmail": "abduljelelahmed@gmail.com",
      "invoiceNumber": "INV-783822",
      "issueDate": "2025-09-25",
      "dueDate": "2025-09-30",
      "billingCurrency": "USD",
      "items": [
        {
          "name": "Qalleet",
          "quantity": 6,
          "price": 2992,
          "total": 17952,
          "id": "it_cbe2jt25"
        }
      ],
      "subtotal": 17952,
      "discount": -2,
      "totalDue": 17954,
      "status": "DRAFT",
      "paymentInfo": {
        "accountName": "2882",
        "accountNumber": "222",
        "achRoutingNo": "22929",
        "bankName": "2229",
        "bankAddress": "2992"
      },
      "reminders": {
        "14days": false,
        "7days": false,
        "3days": false,
        "24hrs": false,
        "dueDate": false
      },
      "activities": [],
      "notes": "",
      "id": "inv_vzm1rfn8"
    },
    {
      "senderName": "Fabulous Enterprise",
      "senderPhone": "+3869892713115",
      "senderAddress": "1331 Hart Ridge Road 48436 Gaines, MI",
      "senderEmail": "info@fabulousenterprise.co",
      "customerName": "abduljelel ahmed",
      "customerPhone": "08154085965",
      "customerAddress": "10, Rufa Isiri Street, Aviele, Edo State",
      "customerEmail": "abduljelelahmed@gmail.com",
      "invoiceNumber": "INV-46749",
      "issueDate": "2025-10-13",
      "dueDate": "2025-09-17",
      "billingCurrency": "EUR",
      "items": [
        {
          "name": "Glass Cleaning",
          "quantity": 1,
          "price": 20,
          "total": 20,
          "id": "it_s0qfiudz"
        },
        {
          "name": "Mechanical Repairs",
          "quantity": 2,
          "price": 33,
          "total": 66,
          "id": "it_5ivvgdv2"
        }
      ],
      "subtotal": 86,
      "discount": 23,
      "totalDue": 63,
      "status": "OVERDUE",
      "paymentInfo": {
        "accountName": "Francei",
        "accountNumber": "8838382992",
        "achRoutingNo": "238383",
        "bankName": "BestBank",
        "bankAddress": "23, Roll-Drive, Nigeria"
      },
      "reminders": {
        "14days": true,
        "7days": false,
        "3days": false,
        "24hrs": true,
        "dueDate": false
      },
      "activities": [],
      "notes": "Thank you for your Patronage",
      "id": "inv_bh4yd12y"
    },
    {
      "senderName": "Fabulous Enterprise",
      "senderPhone": "+3869892713115",
      "senderAddress": "1331 Hart Ridge Road 48436 Gaines, MI",
      "senderEmail": "info@fabulousenterprise.co",
      "customerName": "abduljelel ahmed",
      "customerPhone": "0815408833",
      "customerAddress": "10 Mountain Egle",
      "customerEmail": "abduljel@gmail.com",
      "invoiceNumber": "INV-93187",
      "issueDate": "2025-09-23",
      "dueDate": "2025-09-24",
      "billingCurrency": "EUR",
      "items": [
        {
          "name": "Furniture",
          "quantity": 5,
          "price": 300,
          "total": 1500,
          "id": "it_lsheggw6"
        },
        {
          "name": "Construction",
          "quantity": 1,
          "price": 3000,
          "total": 3000,
          "id": "it_owzl0wif"
        },
        {
          "name": "",
          "quantity": 1,
          "price": 0,
          "total": 0,
          "id": "it_pgeiuuqh"
        }
      ],
      "subtotal": 4500,
      "discount": 90,
      "totalDue": 4410,
      "status": "DRAFT",
      "paymentInfo": {
        "accountName": "Frances",
        "accountNumber": "9023392333",
        "achRoutingNo": "743833",
        "bankName": "Clement Bank",
        "bankAddress": "10 Mountain Road"
      },
      "activities": [],
      "id": "inv_ftgupjxt"
    },
    {
      "senderName": "Fabulous Enterprise",
      "senderPhone": "+3869892713115",
      "senderAddress": "1331 Hart Ridge Road 48436 Gaines, MI",
      "senderEmail": "info@fabulousenterprise.co",
      "customerName": "abduljelel ahmed",
      "customerPhone": "0815408833",
      "customerAddress": "10 Mountain Egle",
      "customerEmail": "abduljel@gmail.com",
      "invoiceNumber": "INV-93187",
      "issueDate": "2025-09-23",
      "dueDate": "2025-09-24",
      "billingCurrency": "EUR",
      "items": [
        {
          "name": "Furniture",
          "quantity": 5,
          "price": 300,
          "total": 1500,
          "id": "it_pemtfj6h"
        },
        {
          "name": "Construction",
          "quantity": 1,
          "price": 3000,
          "total": 3000,
          "id": "it_vdlwut8n"
        },
        {
          "name": "",
          "quantity": 1,
          "price": 0,
          "total": 0,
          "id": "it_6gn1if3h"
        }
      ],
      "subtotal": 4500,
      "discount": 90,
      "totalDue": 4410,
      "status": "DRAFT",
      "paymentInfo": {
        "accountName": "Frances",
        "accountNumber": "9023392333",
        "achRoutingNo": "743833",
        "bankName": "Clement Bank",
        "bankAddress": "10 Mountain Road"
      },
      "activities": [],
      "id": "inv_7cq4ysth"
    },
    {
      "senderName": "Fabulous Enterprise",
      "senderPhone": "+3869892713115",
      "senderAddress": "1331 Hart Ridge Road 48436 Gaines, MI",
      "senderEmail": "info@fabulousenterprise.co",
      "customerName": "abduljelel ahmed",
      "customerPhone": "0815408833",
      "customerAddress": "10 Mountain Egle",
      "customerEmail": "abduljel@gmail.com",
      "invoiceNumber": "INV-93187",
      "issueDate": "2025-09-23",
      "dueDate": "2025-09-24",
      "billingCurrency": "EUR",
      "items": [
        {
          "name": "Furniture",
          "quantity": 5,
          "price": 300,
          "total": 1500,
          "id": "it_90fu17n8"
        },
        {
          "name": "Construction",
          "quantity": 1,
          "price": 3000,
          "total": 3000,
          "id": "it_tjhxs5ks"
        },
        {
          "name": "",
          "quantity": 1,
          "price": 0,
          "total": 0,
          "id": "it_xgrl52w7"
        }
      ],
      "subtotal": 4500,
      "discount": 90,
      "totalDue": 4410,
      "status": "DRAFT",
      "paymentInfo": {
        "accountName": "Frances",
        "accountNumber": "9023392333",
        "achRoutingNo": "743833",
        "bankName": "Clement Bank",
        "bankAddress": "10 Mountain Road"
      },
      "activities": [],
      "id": "inv_qj2ct19t"
    },
    {
      "senderName": "Fabulous Enterprise",
      "senderPhone": "+3869892713115",
      "senderAddress": "1331 Hart Ridge Road 48436 Gaines, MI",
      "senderEmail": "info@fabulousenterprise.co",
      "customerName": "abduljelel ahmed",
      "customerPhone": "0815408833",
      "customerAddress": "10 Mountain Egle",
      "customerEmail": "abduljel@gmail.com",
      "invoiceNumber": "INV-93187",
      "issueDate": "2025-09-23",
      "dueDate": "2025-09-24",
      "billingCurrency": "EUR",
      "items": [
        {
          "name": "Furniture",
          "quantity": 5,
          "price": 300,
          "total": 1500,
          "id": "it_507fkjo8"
        },
        {
          "name": "Construction",
          "quantity": 1,
          "price": 3000,
          "total": 3000,
          "id": "it_h12t79b8"
        },
        {
          "name": "",
          "quantity": 1,
          "price": 0,
          "total": 0,
          "id": "it_17j83ke9"
        }
      ],
      "subtotal": 4500,
      "discount": 90,
      "totalDue": 4410,
      "status": "DRAFT",
      "paymentInfo": {
        "accountName": "Frances",
        "accountNumber": "9023392333",
        "achRoutingNo": "743833",
        "bankName": "Clement Bank",
        "bankAddress": "10 Mountain Road"
      },
      "activities": [],
      "id": "inv_em1drxoo"
    },
    {
      "id": "inv_001",
      "senderName": "Fabulous Enterprise",
      "senderPhone": "+3869892713115",
      "senderAddress": "1331 Hart Ridge Road 48436 Gaines, MI",
      "senderEmail": "info@fabulousenterprise.co",
      "senderLogo": "/logos/fabulous.png",
      "customerName": "Olaniyi Ojo Adewale",
      "customerPhone": "+2348021234567",
      "customerAddress": "1331 Hart Ridge Road 48436 Gaines, MI",
      "customerEmail": "olaniyi@example.com",
      "customerLogo": "/logos/customer1.png",
      "invoiceNumber": "1023902390",
      "issueDate": "2023-03-30",
      "dueDate": "2023-05-19",
      "billingCurrency": "USD",
      "items": [
        {
          "id": "it_001",
          "name": "Email Marketing",
          "quantity": 10,
          "price": 1500,
          "total": 15000,
          "description": "Email campaign management"
        },
        {
          "id": "it_002",
          "name": "Graphic design for emails",
          "quantity": 7,
          "price": 2750,
          "total": 19250
        }
      ],
      "subtotal": 34250,
      "discount": 856.25,
      "totalDue": 33393.75,
      "status": "PAID",
      "paymentInfo": {
        "accountName": "Fabulous Enterprise",
        "accountNumber": "1023902390",
        "achRoutingNo": "123456789",
        "bankName": "Fabulous Bank",
        "bankAddress": "123 Finance Street, NY"
      },
      "activities": [
        {
          "id": "act_001",
          "type": "CREATED",
          "user": "You",
          "timestamp": "2023-09-20T12:20:00Z",
          "description": "Created invoice 1023902390 / Olaniyi Ojo Adewale"
        }
      ]
    },
    {
      "id": "inv_002",
      "senderName": "Fabulous Enterprise",
      "senderPhone": "+3869892713115",
      "senderAddress": "1331 Hart Ridge Road 48436 Gaines, MI",
      "senderEmail": "info@fabulousenterprise.co",
      "customerName": "John Doe",
      "customerPhone": "+2348000000000",
      "customerAddress": "123 Anywhere St",
      "customerEmail": "john@example.com",
      "invoiceNumber": "00239434",
      "issueDate": "2022-12-08",
      "dueDate": "2023-05-19",
      "billingCurrency": "USD",
      "items": [
        {
          "id": "it_003",
          "name": "Video looping effect",
          "quantity": 6,
          "price": 110.5,
          "total": 663
        }
      ],
      "subtotal": 663,
      "discount": 0,
      "totalDue": 663,
      "status": "OVERDUE",
      "paymentInfo": {
        "accountName": "Fabulous Enterprise",
        "accountNumber": "1023902390",
        "achRoutingNo": "123456789",
        "bankName": "Fabulous Bank",
        "bankAddress": "123 Finance Street, NY"
      },
      "activities": []
    }
  ],
  "customers": [
    {
      "id": "cus_001",
      "name": "Olaniyi Ojo Adewale",
      "phone": "+2348021234567",
      "email": "olaniyi@example.com",
      "address": "1331 Hart Ridge Road 48436 Gaines, MI",
      "logo": "/logos/customer1.png"
    },
    {
      "id": "cus_002",
      "name": "John Doe",
      "phone": "+2348000000000",
      "email": "john@example.com",
      "address": "123 Anywhere St",
      "logo": "/logos/customer2.png"
    }
  ]
}